{"options":{},"indexes":[{"v":{"$numberInt":"2"},"key":{"_id":{"$numberInt":"1"}},"name":"_id_","ns":"fet_demo.Customer"},{"v":{"$numberInt":"2"},"key":{"nickname":{"$numberInt":"1"}},"name":"nickname_1","ns":"fet_demo.Customer","background":true},{"v":{"$numberInt":"2"},"key":{"department":{"$numberInt":"1"}},"name":"department_1","ns":"fet_demo.Customer","background":true},{"v":{"$numberInt":"2"},"key":{"personalId":{"$numberInt":"1"}},"name":"personalId_1","ns":"fet_demo.Customer","background":true},{"v":{"$numberInt":"2"},"key":{"mobile":{"$numberInt":"1"}},"name":"mobile_1","ns":"fet_demo.Customer","background":true},{"v":{"$numberInt":"2"},"key":{"accountId":{"$numberInt":"1"}},"name":"accountId_1","ns":"fet_demo.Customer","background":true},{"v":{"$numberInt":"2"},"key":{"relationalfamilyMemberID":{"$numberInt":"1"}},"name":"relationalfamilyMemberID_1","ns":"fet_demo.Customer","background":true},{"v":{"$numberInt":"2"},"key":{"meetingNumber":{"$numberInt":"1"}},"name":"meetingNumber_1","ns":"fet_demo.Customer","background":true},{"v":{"$numberInt":"2"},"key":{"currentVidyoRoomUrl":{"$numberInt":"1"}},"name":"currentVidyoRoomUrl_1","ns":"fet_demo.Customer","background":true},{"v":{"$numberInt":"2"},"key":{"currentVidyoPin":{"$numberInt":"1"}},"name":"currentVidyoPin_1","ns":"fet_demo.Customer","background":true},{"v":{"$numberInt":"2"},"key":{"appName":{"$numberInt":"1"}},"name":"appName_1","ns":"fet_demo.Customer","background":true},{"v":{"$numberInt":"2"},"key":{"version":{"$numberInt":"1"}},"name":"version_1","ns":"fet_demo.Customer","background":true},{"v":{"$numberInt":"2"},"key":{"platform":{"$numberInt":"1"}},"name":"platform_1","ns":"fet_demo.Customer","background":true},{"v":{"$numberInt":"2"},"key":{"companyId":{"$numberInt":"1"}},"name":"companyId_1","ns":"fet_demo.Customer","background":true}],"uuid":"0ef61268a8304d10a8df3bfa263d3d2b"}